Metadata-Version: 2.1
Name: docums-redirects
Version: 1.0.0
Summary: A Docums plugin for dynamic page redirects to prevent broken links.
Home-page: https://github.com/datarobot/docums-redirects
Author: NKDuy
Author-email: kn145660@gmail.com
License: MIT
Keywords: docums redirect
Platform: UNKNOWN
Classifier: Development Status :: 4 - Beta
Classifier: Intended Audience :: Developers
Classifier: Intended Audience :: Information Technology
Classifier: License :: OSI Approved :: MIT License
Classifier: Programming Language :: Python
Classifier: Programming Language :: Python :: 2
Classifier: Programming Language :: Python :: 2.7
Classifier: Programming Language :: Python :: 3
Classifier: Programming Language :: Python :: 3.4
Classifier: Programming Language :: Python :: 3.5
Classifier: Programming Language :: Python :: 3.6
Classifier: Programming Language :: Python :: 3.7
Requires-Python: >=2.7
Provides-Extra: release
